gcpio/gcs.py
gcpio/gdrive.py
gcpio/settings.py
gcpio/utils.py
gcp_io-0.0.0.2.dist-info/METADATA
gcp_io-0.0.0.2.dist-info/WHEEL
gcp_io-0.0.0.2.dist-info/top_level.txt
gcp_io-0.0.0.2.dist-info/RECORD
