Metadata-Version: 2.1
Name: gcp-io
Version: 0.0.0.2
Summary: A package to return files stored in Google drive and Google Cloud Storage as a torch.utils.Dataset that can be used with the torch dataloaders.
Home-page: https://github.com/HimamshuLakkaraju/GCPIO
Author: Himamshu Lakkaraju
Author-email: hlakkaraju@hawk.iit.edu
Classifier: Programming Language :: Python :: 3
Classifier: Programming Language :: Python :: 3.7
Classifier: Operating System :: OS Independent
Requires-Dist: requests (>=2.28.1)
Requires-Dist: torch (>=1.13.0)
Requires-Dist: torchdata (>=0.5.0)
Requires-Dist: torchvision
Requires-Dist: google-auth-oauthlib
Requires-Dist: google-api-python-client
Requires-Dist: google-cloud-storage (>=2.6.0)
Requires-Dist: pillow (>=9.0.1)
Provides-Extra: dev
Requires-Dist: pytest (>=3.7) ; extra == 'dev'
Requires-Dist: twine ; extra == 'dev'
Requires-Dist: pytest-cov (>=4.0.0) ; extra == 'dev'
